graphstat/__init__.py
graphstat/__main__.py
graphstat/graphstat_sqlite3.py
graphstat-0.2.2.dist-info/METADATA
graphstat-0.2.2.dist-info/WHEEL
graphstat-0.2.2.dist-info/RECORD
