Metadata-Version: 2.1
Name: graphstat
Version: 0.2.2
Summary: Graph collection in several forms.
License: MIT
Author: vitroid
Author-email: vitroid@gmail.com
Requires-Python: >=3.11,<4.0
Classifier: License :: OSI Approved :: MIT License
Classifier: Programming Language :: Python :: 3
Classifier: Programming Language :: Python :: 3.11
Classifier: Programming Language :: Python :: 3.12
Requires-Dist: networkx (>=3.4.2,<4.0.0)
Requires-Dist: numpy (>=1.26.2)
